defi_services/__init__.py
defi_services/defi_service.py
defi_services/state_service.py
defi_services/abis/__init__.py
defi_services/abis/erc20_abi.py
defi_services/abis/dex/__init__.py
defi_services/abis/dex/biswap_masterchef_abi.py
defi_services/abis/dex/pancakeswap_masterchef_abi.py
defi_services/abis/lending_pool/__init__.py
defi_services/abis/lending_pool/aave_v3_incentives_abi.py
defi_services/abis/lending_pool/aave_v3_lending_pool_abi.py
defi_services/abis/lending_pool/aave_v3_oracle_abi.py
defi_services/abis/lending_pool/alpaca_fair_launch_abi.py
defi_services/abis/lending_pool/alpaca_vault_abi.py
defi_services/abis/lending_pool/alpaca_vault_config_abi.py
defi_services/abis/lending_pool/chain_link_abi.py
defi_services/abis/lending_pool/chef_incentives_controller.py
defi_services/abis/lending_pool/cream_comptroller_abi.py
defi_services/abis/lending_pool/cream_lens_abi.py
defi_services/abis/lending_pool/ctoken_abi.py
defi_services/abis/lending_pool/lending_pool_abi.py
defi_services/abis/lending_pool/oracle_abi.py
defi_services/abis/lending_pool/staked_incentives_abi.py
defi_services/abis/lending_pool/trava_lending_pool_abi.py
defi_services/abis/lending_pool/trava_oracle_abi.py
defi_services/abis/lending_pool/valas_multi_fee_distribution.py
defi_services/abis/lending_pool/venus_comptroller_abi.py
defi_services/abis/lending_pool/venus_lens_abi.py
defi_services/abis/lending_pool/venus_lens_abi_v1.py
defi_services/abis/vault/__init__.py
defi_services/abis/vault/incentive_abi.py
defi_services/abis/vault/trava_vault_abi.py
defi_services/abis/vault/valuator_abi.py
defi_services/abis/vault/ve_abi.py
defi_services/constants/__init__.py
defi_services/constants/chain_constant.py
defi_services/constants/contract_address.py
defi_services/constants/db_constant.py
defi_services/constants/mapping_constant.py
defi_services/constants/time_constant.py
defi_services/lending_pools/__init__.py
defi_services/lending_pools/aave_v2_service.py
defi_services_lib-1.0.7.dist-info/LICENSE
defi_services_lib-1.0.7.dist-info/METADATA
defi_services_lib-1.0.7.dist-info/WHEEL
defi_services_lib-1.0.7.dist-info/top_level.txt
defi_services_lib-1.0.7.dist-info/RECORD
